matplotlib_set_diagrams/__init__.py
matplotlib_set_diagrams/_diagram_classes.py
matplotlib_set_diagrams/_utils.py
matplotlib_set_diagrams-0.0.2.dist-info/LICENSE.txt
matplotlib_set_diagrams-0.0.2.dist-info/METADATA
matplotlib_set_diagrams-0.0.2.dist-info/WHEEL
matplotlib_set_diagrams-0.0.2.dist-info/top_level.txt
matplotlib_set_diagrams-0.0.2.dist-info/RECORD
