Metadata-Version: 2.1
Name: matplotlib_set_diagrams
Version: 0.0.2
Summary: Python drawing utilities for Venn and Euler diagrams visualizing the relationships between two or more sets.
Author-email: Paul Brodersen <paulbrodersen+matplotlib_set_diagrams@gmail.com>
License: GNU General Public License v3 (GPLv3)
Project-URL: Repository, https://github.com/paulbrodersen/matplotlib_set_diagrams
Project-URL: Documentation, https://matplotlib-set-diagrams.readthedocs.io/en/latest/
Keywords: matplotlib,Euler diagram,Venn diagram,set,visualisation,visualization
Classifier: Development Status :: 4 - Beta
Classifier: Intended Audience :: Science/Research
Classifier: License :: OSI Approved :: GNU General Public License v3 (GPLv3)
Classifier: Operating System :: OS Independent
Classifier: Programming Language :: Python :: 3
Classifier: Topic :: Scientific/Engineering :: Visualization
Requires-Python: >3.6
License-File: LICENSE.txt
Requires-Dist: numpy
Requires-Dist: scipy
Requires-Dist: matplotlib
Requires-Dist: shapely
Requires-Dist: wordcloud
Provides-Extra: docs
Requires-Dist: sphinx ; extra == 'docs'
Requires-Dist: sphinx-rtd-theme ; extra == 'docs'
Requires-Dist: numpydoc ; extra == 'docs'
Requires-Dist: sphinx-gallery ; extra == 'docs'
Requires-Dist: Pillow ; extra == 'docs'
Provides-Extra: tests
Requires-Dist: pytest ; extra == 'tests'
Requires-Dist: pytest-mpl ; extra == 'tests'
Requires-Dist: pytest-cov ; extra == 'tests'
